dfh/__init__.py
dfh/core.py
dfh/exceptions.py
digest_fusion_hashing-1.0.3.dist-info/licenses/LICENSE
digest_fusion_hashing-1.0.3.dist-info/METADATA
digest_fusion_hashing-1.0.3.dist-info/WHEEL
digest_fusion_hashing-1.0.3.dist-info/top_level.txt
digest_fusion_hashing-1.0.3.dist-info/RECORD
