Metadata-Version: 2.4
Name: digest-fusion-hashing
Version: 1.0.3
Summary: A secure data integrity reinforcement technique using dual digest fusion with randomized splitting.
Home-page: https://github.com/mGobb1/digest-fusion-hashing
Author: Miguel Gobbi
License: MIT License
Project-URL: Homepage, https://github.com/mGobb1/digest-fusion-hashing
Project-URL: Repository, https://github.com/mGobb1/digest-fusion-hashing
Requires-Python: >=3.8
License-File: LICENSE
Dynamic: home-page
Dynamic: license-file
Dynamic: requires-python
